[
  {
    "Context Size (Documents)": "10",
    "Position of Answer (Gold Index)": 0,
    "Accuracy (%)": 61.39359698681732,
    "Correct": 1630,
    "Total": 2655
  },
  {
    "Context Size (Documents)": "10",
    "Position of Answer (Gold Index)": 4,
    "Accuracy (%)": 57.02448210922787,
    "Correct": 1514,
    "Total": 2655
  },
  {
    "Context Size (Documents)": "10",
    "Position of Answer (Gold Index)": 9,
    "Accuracy (%)": 55.442561205273066,
    "Correct": 1472,
    "Total": 2655
  }
]